aiowamp/__init__.py
aiowamp/args_mixin.py
aiowamp/err.py
aiowamp/errors.py
aiowamp/id.py
aiowamp/maybe_awaitable.py
aiowamp/message.py
aiowamp/msg.py
aiowamp/msg.pyi
aiowamp/py.typed
aiowamp/session.py
aiowamp/transport.py
aiowamp/uri.py
aiowamp/uri_map.py
aiowamp/client/__init__.py
aiowamp/client/auth.py
aiowamp/client/bwlist.py
aiowamp/client/call.py
aiowamp/client/client.py
aiowamp/client/conn.py
aiowamp/client/enum.py
aiowamp/client/event.py
aiowamp/client/invocation.py
aiowamp/client/procedure_runner.py
aiowamp/client/roles.py
aiowamp/client/utils.py
aiowamp/serializers/__init__.py
aiowamp/serializers/json.py
aiowamp/serializers/msgpack.py
aiowamp/templ/__init__.py
aiowamp/templ/handler.py
aiowamp/templ/template.py
aiowamp/templ/entry_point/__init__.py
aiowamp/templ/entry_point/args.py
aiowamp/templ/entry_point/code.py
aiowamp/templ/entry_point/entry.py
aiowamp/transports/__init__.py
aiowamp/transports/raw_socket.py
aiowamp/transports/web_socket.py
aiowamp-0.1.1.dist-info/LICENSE
aiowamp-0.1.1.dist-info/METADATA
aiowamp-0.1.1.dist-info/WHEEL
aiowamp-0.1.1.dist-info/top_level.txt
aiowamp-0.1.1.dist-info/RECORD
