Metadata-Version: 2.1
Name: aiowamp
Version: 0.1.1
Summary: UNKNOWN
Home-page: https://github.com/gieseladev/aiowamp
Author: Giesela Inc.
Author-email: team@giesela.dev
License: MIT
Platform: UNKNOWN
Requires-Dist: msgpack
Requires-Dist: websockets
